{"similarity": "http://www.freesound.org/api/sounds/127796/similar/", "channels": 2, "duration": 1160.46, "samplerate": 48000.0, "preview-hq-ogg": "http://www.freesound.org/data/previews/127/127796_28867-hq.ogg", "id": 127796, "preview-lq-ogg": "http://www.freesound.org/data/previews/127/127796_28867-lq.ogg", "ref": "http://www.freesound.org/api/sounds/127796/", "analysis_stats": "http://www.freesound.org/api/sounds/127796/analysis/", "tags": ["denmark", "rain", "field-recording", "lawnmower", "tinroof"], "serve": "http://www.freesound.org/api/sounds/127796/serve/", "spectral_m": "http://www.freesound.org/data/displays/127/127796_28867_spec_M.jpg", "spectral_l": "http://www.freesound.org/data/displays/127/127796_28867_spec_L.jpg", "user": {"username": "inchadney", "url": "http://www.freesound.org/people/inchadney/", "ref": "http://www.freesound.org/api/people/inchadney/"}, "preview-hq-mp3": "http://www.freesound.org/data/previews/127/127796_28867-hq.mp3", "analysis_frames": "http://www.freesound.org/data/analysis/127/127796_28867_frames.json", "license": "http://creativecommons.org/licenses/by/3.0/", "url": "http://www.freesound.org/people/inchadney/sounds/127796/", "type": "wav", "preview-lq-mp3": "http://www.freesound.org/data/previews/127/127796_28867-lq.mp3", "original_filename": "Rain.WAV", "waveform_l": "http://www.freesound.org/data/displays/127/127796_28867_wave_L.png", "waveform_m": "http://www.freesound.org/data/displays/127/127796_28867_wave_M.png", "pack": "http://www.freesound.org/api/packs/2793/"}